main/__init__.py
main/Test/AbstractParserTest.py
main/Test/CSVParserTest.py
main/Test/DataManagerfactoryTest.py
main/Test/JsonParserTest.py
main/Test/XmlParserTest.py
main/Test/__init__.py
main/Test/test_configuration.py
main/Test/test_entity.py
main/data_processor/__init__.py
main/data_processor/configuration.py
main/data_processor/entity.py
main/data_processor/performanceAnalizer.py
main/data_transformer/__init__.py
main/data_transformer/abstract_parser.py
main/data_transformer/csv_parser.py
main/data_transformer/custom_exception.py
main/data_transformer/data_manager_factory.py
main/data_transformer/json_parser.py
main/data_transformer/xml_parser.py
myPerformanceAnalyzer2-0.0.1.dist-info/LICENSE.txt
myPerformanceAnalyzer2-0.0.1.dist-info/METADATA
myPerformanceAnalyzer2-0.0.1.dist-info/WHEEL
myPerformanceAnalyzer2-0.0.1.dist-info/top_level.txt
myPerformanceAnalyzer2-0.0.1.dist-info/RECORD
